opynsim/__init__.py
opynsim/__main__.py
opynsim/_opynsim_native.pyd
opynsim/tps3d.py
opynsim/ui/__init__.py
opynsim-0.0.2.dist-info/METADATA
opynsim-0.0.2.dist-info/WHEEL
opynsim-0.0.2.dist-info/RECORD
