Metadata-Version: 2.3
Name: opynsim
Version: 0.0.2
Summary: Musculoskeletal Modelling Simplified
Project-URL: Source Code, https://github.com/opynsim/opynsim
Author: Adam Kewley
Author-email: contact@adamkewley.com
License: Apache 2.0
Platform: Windows
Requires-Python: >=3.12
Requires-Dist: numpy>=1.23.5
Keywords: biomechanics, musculoskeletal, opensim, simulation
Classifier: Operating System :: Microsoft :: Windows
Classifier: Development Status :: 1 - Planning
Classifier: License :: OSI Approved :: Apache Software License
Classifier: Intended Audience :: Developers
Classifier: Intended Audience :: Science/Research
Classifier: Topic :: Scientific/Engineering
Classifier: Programming Language :: Python
Classifier: Programming Language :: Python :: 3
Classifier: Programming Language :: C++
